akview.py
pyak_view-0.0.1.dist-info/METADATA
pyak_view-0.0.1.dist-info/WHEEL
pyak_view-0.0.1.dist-info/entry_points.txt
pyak_view-0.0.1.dist-info/top_level.txt
pyak_view-0.0.1.dist-info/zip-safe
pyak_view-0.0.1.dist-info/RECORD
